pywifi/__init__.py
pywifi/control_connection.py
pywifi/control_peripheral.py
pywifi/model.py
pywifi/win_wifi_config.xml
pywifi_controls-0.8.dist-info/LICENSE
pywifi_controls-0.8.dist-info/METADATA
pywifi_controls-0.8.dist-info/WHEEL
pywifi_controls-0.8.dist-info/top_level.txt
pywifi_controls-0.8.dist-info/RECORD
