Metadata-Version: 2.1
Name: pywifi-controls
Version: 0.8
Summary: Python module to modify screen brightness on Linux, Windows and macOS
Author-email: Vignesh Sivanandha Rao <svignesh1793@gmail.com>
License: MIT License
Project-URL: Homepage, https://github.com/thevickypedia/pywifi-controls
Project-URL: Docs, https://thevickypedia.github.io/pywifi-controls/
Project-URL: Source, https://github.com/thevickypedia/pywifi-controls
Project-URL: Bug Tracker, https://github.com/thevickypedia/pywifi-controls/issues
Project-URL: Release Notes, https://github.com/thevickypedia/pywifi-controls/blob/main/release_notes.rst
Keywords: pywifi,display-settings,brightness-control
Classifier: Development Status :: 5 - Production/Stable
Classifier: Programming Language :: Python :: 3.9
Classifier: License :: OSI Approved :: MIT License
Classifier: Operating System :: MacOS :: MacOS X
Classifier: Operating System :: Microsoft :: Windows
Classifier: Operating System :: POSIX :: Linux
Classifier: Topic :: Terminals :: Terminal Emulators/X Terminals
Requires-Python: >=3
License-File: LICENSE
Requires-Dist: python-dotenv>=0.21.0
Requires-Dist: pyobjc-framework-CoreWLAN; platform_system == "Darwin"
Requires-Dist: Jinja2==3.1.2; platform_system == "Windows"
Provides-Extra: dev
Requires-Dist: pre-commit; extra == "dev"
